trajectorama/__init__.py
trajectorama/_louvain.py
trajectorama/pan_dag.py
trajectorama/trajectorama.py
trajectorama/utils.py
trajectorama-0.2.dist-info/LICENSE
trajectorama-0.2.dist-info/METADATA
trajectorama-0.2.dist-info/WHEEL
trajectorama-0.2.dist-info/top_level.txt
trajectorama-0.2.dist-info/RECORD
